tacobridge/__init__.py
tacobridge/_constants.py
tacobridge/_exceptions.py
tacobridge/_logging.py
tacobridge/_metadata.py
tacobridge/_types.py
tacobridge/api.py
tacobridge/execute.py
tacobridge/finalize.py
tacobridge/plan.py
tacobridge-0.3.0.dist-info/METADATA
tacobridge-0.3.0.dist-info/WHEEL
tacobridge-0.3.0.dist-info/licenses/LICENSE
tacobridge-0.3.0.dist-info/RECORD
