Metadata-Version: 2.4
Name: tacobridge
Version: 0.3.0
Summary: Format conversion and subset export for TACO datasets
License-Expression: MIT
License-File: LICENSE
Keywords: earth-observation,geospatial,machine-learning,satellite-imagery,remote-sensing,ai-ready-datasets,data-pipeline
Author: Cesar Aybar
Author-email: cesar.aybar@uv.es
Requires-Python: >=3.11,<3.14
Classifier: Development Status :: 4 - Beta
Classifier: Intended Audience :: Science/Research
Classifier: License :: OSI Approved :: MIT License
Classifier: Operating System :: OS Independent
Classifier: Programming Language :: Python :: 3
Classifier: Programming Language :: Python :: 3.11
Classifier: Programming Language :: Python :: 3.12
Classifier: Programming Language :: Python :: 3.13
Classifier: Topic :: Scientific/Engineering :: Artificial Intelligence
Classifier: Topic :: Scientific/Engineering :: GIS
Classifier: Typing :: Typed
Requires-Dist: tacoreader (>=2.4.13)
Requires-Dist: tacotoolbox (>=0.26.0)
Project-URL: Bug Tracker, https://github.com/tacofoundation/tacobridge/issues
Project-URL: Changelog, https://github.com/tacofoundation/tacobridge/releases
Project-URL: Documentation, https://tacofoundation.github.io/tacobridge
Project-URL: Repository, https://github.com/tacofoundation/tacobridge
